paylink_tracer/__init__.py
paylink_tracer/constants.py
paylink_tracer/exceptions.py
paylink_tracer/tracer.py
paylink_tracer/utils.py
paylink_tracer-0.2.1.dist-info/METADATA
paylink_tracer-0.2.1.dist-info/WHEEL
paylink_tracer-0.2.1.dist-info/licenses/LICENSE
paylink_tracer-0.2.1.dist-info/RECORD
