Metadata-Version: 2.4
Name: paylink-tracer
Version: 0.2.1
Summary: Lightweight Python SDK for tracing Paylink payment operations - automatically capture and send payment data to Paylink API
Project-URL: Homepage, https://github.com/paylink/paylink-tracer
Project-URL: Repository, https://github.com/paylink/paylink-tracer
Project-URL: Documentation, https://github.com/paylink/paylink-tracer#readme
Project-URL: Bug Tracker, https://github.com/paylink/paylink-tracer/issues
Author-email: PayLink <paylinkmcp@gmail.com>
Maintainer-email: PayLink <paylinkmcp@gmail.com>
License: MIT License
License-File: LICENSE
Keywords: apm,distributed-tracing,mcp,monitoring,mpesa,observability,paylink,payments,telemetry,tracing
Classifier: Development Status :: 3 - Alpha
Classifier: Intended Audience :: Developers
Classifier: License :: OSI Approved :: MIT License
Classifier: Operating System :: OS Independent
Classifier: Programming Language :: Python :: 3
Classifier: Programming Language :: Python :: 3.8
Classifier: Programming Language :: Python :: 3.9
Classifier: Programming Language :: Python :: 3.10
Classifier: Programming Language :: Python :: 3.11
Classifier: Programming Language :: Python :: 3.12
Classifier: Programming Language :: Python :: 3.13
Classifier: Topic :: Office/Business :: Financial
Classifier: Topic :: Software Development :: Libraries :: Python Modules
Classifier: Topic :: System :: Monitoring
Requires-Python: >=3.9
Requires-Dist: httpx>=0.24.0
Provides-Extra: dev
Requires-Dist: black>=23.0.0; extra == 'dev'
Requires-Dist: hatch>=1.14.1; extra == 'dev'
Requires-Dist: mypy>=1.0.0; extra == 'dev'
Requires-Dist: pytest-asyncio>=0.21.0; extra == 'dev'
Requires-Dist: pytest-cov>=4.0.0; extra == 'dev'
Requires-Dist: pytest>=7.0.0; extra == 'dev'
Requires-Dist: ruff>=0.1.0; extra == 'dev'
Requires-Dist: twine>=6.2.0; extra == 'dev'
Provides-Extra: dotenv
Requires-Dist: python-dotenv>=1.0.1; extra == 'dotenv'
